[{"id":3310200006,"name":"BLANCERAN"},{"id":3310200008,"name":"BRANGKAL"},{"id":3310200017,"name":"GEMPOL"},{"id":3310200001,"name":"JAMBEYAN"},{"id":3310200019,"name":"JEBLOG"},{"id":3310200002,"name":"JUNGKARE"},{"id":3310200014,"name":"JURANGJERO"},{"id":3310200003,"name":"KADIREJO"},{"id":3310200010,"name":"KARANGAN"},{"id":3310200011,"name":"KARANGANOM"},{"id":3310200015,"name":"NGABEYAN"},{"id":3310200012,"name":"PADAS"},{"id":3310200018,"name":"PONDOK"},{"id":3310200013,"name":"SOROPATEN"},{"id":3310200004,"name":"TARUBASAN"},{"id":3310200005,"name":"TROSO"}]