[{"id":1202050040,"name":"ADIAN JIOR"},{"id":1202050007,"name":"AEK BANIR"},{"id":1202050063,"name":"AEK MATA"},{"id":1202050070,"name":"DALAN LIDANG"},{"id":1202050030,"name":"DARUSSALAM"},{"id":1202050052,"name":"GUNUNG BARANI"},{"id":1202050044,"name":"GUNUNG MANAON"},{"id":1202050049,"name":"GUNUNG TUA JAE"},{"id":1202050067,"name":"GUNUNG TUA JULU"},{"id":1202050068,"name":"GUNUNG TUA TONGA"},{"id":1202050064,"name":"HUTA LOMBANG LUBIS"},{"id":1202050048,"name":"IPAR BONDAR"},{"id":1202050047,"name":"KAMPUNG PADANG"},{"id":1202050045,"name":"KAYU JATI"},{"id":1202050032,"name":"KOTA SIANTAR"},{"id":1202050069,"name":"LUMBAN PASIR"},{"id":1202050050,"name":"MANYABAR"},{"id":1202050075,"name":"MANYABAR JAE"},{"id":1202050065,"name":"PAGARAN TONGA"},{"id":1202050074,"name":"PANGGORENGAN"},{"id":1202050035,"name":"PANYABUNGAN I"},{"id":1202050033,"name":"PANYABUNGAN II"},{"id":1202050034,"name":"PANYABUNGAN III"},{"id":1202050039,"name":"PANYABUNGAN JAE"},{"id":1202050037,"name":"PANYABUNGAN JULU"},{"id":1202050038,"name":"PANYABUNGAN TONGA"},{"id":1202050019,"name":"PARBANGUNAN"},{"id":1202050036,"name":"PASAR HILIR"},{"id":1202050029,"name":"PIDOLI DOLOK"},{"id":1202050028,"name":"PIDOLI LOMBANG"},{"id":1202050073,"name":"SABA JAMBU"},{"id":1202050062,"name":"SALAMBUE"},{"id":1202050051,"name":"SARAK MATUA"},{"id":1202050046,"name":"SIGALAPANG JULU"},{"id":1202050071,"name":"SIOBON JAE"},{"id":1202050031,"name":"SIOBON JULU"},{"id":1202050018,"name":"SIPAGA - PAGA"},{"id":1202050072,"name":"SIPOLU POLU"},{"id":1202050066,"name":"SOPO BATU"}]