[{"id":3603130,"name":"BALARAJA"},{"id":3603030,"name":"CIKUPA"},{"id":3603081,"name":"CISAUK"},{"id":3603010,"name":"CISOKA"},{"id":3603050,"name":"CURUG"},{"id":3603141,"name":"GUNUNG KALER"},{"id":3603021,"name":"JAMBE"},{"id":3603131,"name":"JAYANTI"},{"id":3603051,"name":"KELAPA DUA"},{"id":3603161,"name":"KEMIRI"},{"id":3603210,"name":"KOSAMBI"},{"id":3603140,"name":"KRESEK"},{"id":3603150,"name":"KRONJO"},{"id":3603060,"name":"LEGOK"},{"id":3603160,"name":"MAUK"},{"id":3603151,"name":"MEKAR BARU"},{"id":3603070,"name":"PAGEDANGAN"},{"id":3603190,"name":"PAKUHAJI"},{"id":3603040,"name":"PANONGAN"},{"id":3603120,"name":"PASARKEMIS"},{"id":3603170,"name":"RAJEG"},{"id":3603180,"name":"SEPATAN"},{"id":3603181,"name":"SEPATAN TIMUR"},{"id":3603121,"name":"SINDANG JAYA"},{"id":3603011,"name":"SOLEAR"},{"id":3603162,"name":"SUKADIRI"},{"id":3603132,"name":"SUKAMULYA"},{"id":3603200,"name":"TELUKNAGA"},{"id":3603020,"name":"TIGARAKSA"}]