[{"id":3518050010,"name":"BABADAN"},{"id":3518050015,"name":"BANARAN"},{"id":3518050009,"name":"BATEMBAT"},{"id":3518050011,"name":"BODOR"},{"id":3518050005,"name":"GONDANG"},{"id":3518050008,"name":"JAMPES"},{"id":3518050002,"name":"JATIGREGES"},{"id":3518050014,"name":"JETIS"},{"id":3518050001,"name":"JOHO"},{"id":3518050018,"name":"KEPANJEN"},{"id":3518050007,"name":"MLANDANGAN"},{"id":3518050012,"name":"PACE WETAN"},{"id":3518050004,"name":"PACEKULON"},{"id":3518050017,"name":"PLOSOHARJO"},{"id":3518050003,"name":"SANAN"}]