[{"id":6306100008,"name":"BARUH KEMBANG"},{"id":6306100007,"name":"BELAH PAIKAT"},{"id":6306100023,"name":"HAKURUNG"},{"id":6306100019,"name":"HAMAYUNG"},{"id":6306100020,"name":"HAMAYUNG UTARA"},{"id":6306100005,"name":"MANDALA MURUNG MESJID"},{"id":6306100016,"name":"MURUNG RAYA"},{"id":6306100021,"name":"PAHARANGAN"},{"id":6306100010,"name":"PAKAN DALAM"},{"id":6306100001,"name":"PAKAPURAN KECIL"},{"id":6306100014,"name":"PANDAK DAUN"},{"id":6306100002,"name":"PANGGANDINGAN"},{"id":6306100011,"name":"PARAMAIAN"},{"id":6306100013,"name":"PASUNGKAN"},{"id":6306100006,"name":"SUNGAI GARUDA"},{"id":6306100004,"name":"SUNGAI MANDALA"},{"id":6306100012,"name":"TALUK HAUR"},{"id":6306100003,"name":"TAMBAK BITIN"},{"id":6306100015,"name":"TELUK LABAK"}]