[{"id":7101060010,"name":"ABAK"},{"id":7101060003,"name":"BAKAN"},{"id":7101060011,"name":"BOMBANON"},{"id":7101060013,"name":"KOPANDAKAN II"},{"id":7101060006,"name":"LOLAYAN"},{"id":7101060002,"name":"MATALI BARU"},{"id":7101060014,"name":"MENGKANG"},{"id":7101060012,"name":"MOPAIT"},{"id":7101060001,"name":"MOPUSI"},{"id":7101060004,"name":"TANOYAN SELATAN"},{"id":7101060005,"name":"TANOYAN UTARA"},{"id":7101060009,"name":"TAPA AOG"},{"id":7101060008,"name":"TUNGOI I"},{"id":7101060007,"name":"TUNGOI II"}]