[{"id":6108070002,"name":"BAHENAP"},{"id":6108070010,"name":"KALIS RAYA"},{"id":6108070009,"name":"KENSURAY"},{"id":6108070006,"name":"NANGA DANAU"},{"id":6108070005,"name":"NANGA KALIS"},{"id":6108070003,"name":"NANGA LEBANGAN"},{"id":6108070001,"name":"NANGA RAUN"},{"id":6108070004,"name":"NANGA SEBINTANG"},{"id":6108070007,"name":"NANGA TUBUK"},{"id":6108070015,"name":"PAYUNGAN"},{"id":6108070017,"name":"RANTAU BUMBUN"},{"id":6108070008,"name":"RANTAU KALIS"},{"id":6108070016,"name":"RIBANG KADENG"},{"id":6108070014,"name":"SEGIAM"},{"id":6108070012,"name":"SEMERANTAU"},{"id":6108070013,"name":"TAPANG DA'AN"},{"id":6108070011,"name":"TEKUDAK"}]