[{"id":1213040010,"name":"BALAI KASIH"},{"id":1213040009,"name":"BEKIUNG"},{"id":1213040019,"name":"BELA RAKYAT"},{"id":1213040003,"name":"BERUAM"},{"id":1213040004,"name":"BESADI"},{"id":1213040011,"name":"DALAN NAMAN"},{"id":1213040001,"name":"GARUNGGANG"},{"id":1213040008,"name":"NAMO MBELIN"},{"id":1213040002,"name":"PARIT BINDU"},{"id":1213040012,"name":"PEKAN KUALA"},{"id":1213040013,"name":"PERKEBUNAN BEKIUN"},{"id":1213040005,"name":"PERKEBUNAN BLANGKAHAN"},{"id":1213040007,"name":"RAJA TENGAH"},{"id":1213040006,"name":"SEI PENJARA"},{"id":1213040018,"name":"SIDO MAKMUR"},{"id":1213040017,"name":"SUKA DAMAI"}]