[{"id":3517030004,"name":"BLIMBING"},{"id":3517030008,"name":"BUGASUR KEDALEMAN"},{"id":3517030017,"name":"GEMPOL LEGUNDI"},{"id":3517030014,"name":"GODONG"},{"id":3517030009,"name":"GUDO"},{"id":3517030003,"name":"JAPANAN"},{"id":3517030002,"name":"KEDUNGTURI"},{"id":3517030012,"name":"KREMBANGAN"},{"id":3517030015,"name":"MEJOYOLOSARI"},{"id":3517030005,"name":"MENTAOS"},{"id":3517030011,"name":"PESANGGRAHAN"},{"id":3517030016,"name":"PLUMBON GAMBANG"},{"id":3517030001,"name":"PUCANGRO"},{"id":3517030013,"name":"SEPANYUL"},{"id":3517030006,"name":"SUKOIBER"},{"id":3517030007,"name":"SUKOPINGGIR"},{"id":3517030018,"name":"TANGGUNGAN"},{"id":3517030010,"name":"WANGKALKEPUH"}]