[{"id":8103050,"name":"AMAHAI"},{"id":8103010,"name":"BANDA"},{"id":8103110,"name":"LEIHITU"},{"id":8103111,"name":"LEIHITU BARAT"},{"id":8103081,"name":"NUSALAUT"},{"id":8103090,"name":"P. HARUKU"},{"id":8103100,"name":"SALAHUTU"},{"id":8103080,"name":"SAPARUA"},{"id":8103082,"name":"SAPARUA TIMUR"},{"id":8103140,"name":"SERAM UTARA"},{"id":8103141,"name":"SERAM UTARA BARAT"},{"id":8103142,"name":"SERAM UTARA TIMUR KOBI"},{"id":8103143,"name":"SERAM UTARA TIMUR SETI"},{"id":8103040,"name":"TEHORU"},{"id":8103052,"name":"TELUK ELPAPUTIH"},{"id":8103041,"name":"TELUTIH"},{"id":8103060,"name":"TEON NILA SERUA"},{"id":8103051,"name":"kota MASOHI"}]