[{"id":1610011002,"name":"BERINGIN DALAM"},{"id":1610011001,"name":"IBUL DALAM"},{"id":1610011009,"name":"KAYU ARA"},{"id":1610011003,"name":"KUANG DALAM BARAT"},{"id":1610011012,"name":"KUANG DALAM TIMUR"},{"id":1610011004,"name":"LUBUK TUNGGAL"},{"id":1610011013,"name":"SUKANANTI"},{"id":1610011011,"name":"SUNUR"},{"id":1610011006,"name":"TAMBANG RAMBANG"},{"id":1610011007,"name":"TANGAI"},{"id":1610011010,"name":"TANJUNG BULAN"},{"id":1610011008,"name":"TANJUNG MIRING"},{"id":1610011005,"name":"ULAK SEGARA"}]