[{"id":3515170021,"name":"BARENGKRAJAN"},{"id":3515170005,"name":"GAMPING"},{"id":3515170010,"name":"JATIKALANG"},{"id":3515170004,"name":"JERUK GAMPING"},{"id":3515170007,"name":"JUNWANGI"},{"id":3515170003,"name":"KATRUNGAN"},{"id":3515170011,"name":"KEBOHARAN"},{"id":3515170013,"name":"KEMASAN"},{"id":3515170017,"name":"KRATON"},{"id":3515170016,"name":"KRIAN"},{"id":3515170012,"name":"PONOKAWAN"},{"id":3515170002,"name":"SEDENGAN MIJEN"},{"id":3515170014,"name":"SIDOMOJO"},{"id":3515170018,"name":"SIDOMULYO"},{"id":3515170022,"name":"SIDOREJO"},{"id":3515170015,"name":"TAMBAK KEMERAKAN"},{"id":3515170006,"name":"TERIK"},{"id":3515170008,"name":"TERUNG KULON"},{"id":3515170009,"name":"TERUNG WETAN"},{"id":3515170001,"name":"TROPODO"},{"id":3515170020,"name":"WATUGOLONG"}]