[{"id":7409122015,"name":"BIRA"},{"id":7409122010,"name":"EERINERE"},{"id":7409122009,"name":"KUROLABU"},{"id":7409122013,"name":"LABELETE"},{"id":7409122007,"name":"LAMOAHI"},{"id":7409122006,"name":"LANOSANGIA"},{"id":7409122003,"name":"LELAMO"},{"id":7409122005,"name":"PEBAOA"},{"id":7409122004,"name":"PETETEAA"},{"id":7409122008,"name":"TORUMBIA"},{"id":7409122001,"name":"ULUNAMBO"},{"id":7409122011,"name":"WAMBOULE"},{"id":7409122002,"name":"WAODE BURI"},{"id":7409122014,"name":"WOWONGA JAYA"}]