[{"id":1213020026,"name":"ADIN TENGAH"},{"id":1213020015,"name":"BANDAR TELU"},{"id":1213020027,"name":"LAU LUGUR"},{"id":1213020008,"name":"LAU TEPU"},{"id":1213020018,"name":"MINTA KASIH"},{"id":1213020020,"name":"NAMAN JAHE"},{"id":1213020009,"name":"PAMA TAMBUNAN"},{"id":1213020028,"name":"PANCUR IDO"},{"id":1213020006,"name":"PARANGGUAM"},{"id":1213020010,"name":"PERKEBUNAN GLUGUR LANGKAT"},{"id":1213020007,"name":"PERKEBUNAN TAMBUNAN"},{"id":1213020021,"name":"PERKEBUNAN TANJUNG KELILING"},{"id":1213020025,"name":"PONCO WARNO"},{"id":1213020019,"name":"TANJUNG LANGKAT"},{"id":1213020016,"name":"TURANGI"},{"id":1213020005,"name":"UJUNG BANDAR"},{"id":1213020017,"name":"UJUNG TERAN"}]