[{"id":1610042007,"name":"PENYANDINGAN"},{"id":1610042008,"name":"PINANG JAYA"},{"id":1610042010,"name":"PINANG MAS"},{"id":1610042006,"name":"SERIJABO"},{"id":1610042013,"name":"SERIJABO BARU"},{"id":1610042004,"name":"SUNGAI PINANG"},{"id":1610042009,"name":"SUNGAI PINANG I"},{"id":1610042005,"name":"SUNGAI PINANG II"},{"id":1610042003,"name":"SUNGAI PINANG III"},{"id":1610042011,"name":"SUNGAI PINANG LAGATI"},{"id":1610042012,"name":"SUNGAI PINANG NIBUNG"},{"id":1610042002,"name":"TALANG DUKUN"},{"id":1610042001,"name":"TANJUNG SERIAN"}]