[{"id":1214040,"name":"AMANDRAYA"},{"id":1214041,"name":"ARAMO"},{"id":1214066,"name":"BORONADU"},{"id":1214031,"name":"FANAYAMA"},{"id":1214060,"name":"GOMO"},{"id":1214010,"name":"HIBALA"},{"id":1214081,"name":"HILIMEGAI"},{"id":1214084,"name":"HILISALAWAAHE"},{"id":1214072,"name":"HURUNA"},{"id":1214064,"name":"IDANOTAE"},{"id":1214050,"name":"LAHUSA"},{"id":1214070,"name":"LOLOMATUA"},{"id":1214080,"name":"LOLOWA'U"},{"id":1214035,"name":"LUAHAGUNDRE MANIAMOLO"},{"id":1214033,"name":"MANIAMOLO"},{"id":1214034,"name":"MAZINO"},{"id":1214062,"name":"MAZO"},{"id":1214083,"name":"ONOHAZUMBA"},{"id":1214036,"name":"ONOLALU"},{"id":1214082,"name":"OOU"},{"id":1214020,"name":"PULAU-PULAU BATU"},{"id":1214023,"name":"PULAU-PULAU BATU BARAT"},{"id":1214021,"name":"PULAU-PULAU BATU TIMUR"},{"id":1214024,"name":"PULAU-PULAU BATU UTARA"},{"id":1214051,"name":"SIDUAORI"},{"id":1214022,"name":"SIMUK"},{"id":1214052,"name":"SOMAMBAWA"},{"id":1214061,"name":"SUSUA"},{"id":1214011,"name":"TANAH MASA"},{"id":1214030,"name":"TELUK DALAM"},{"id":1214032,"name":"TOMA"},{"id":1214065,"name":"ULUIDANOTAE"},{"id":1214071,"name":"ULUNOYO"},{"id":1214042,"name":"ULUSUSUA"},{"id":1214063,"name":"UMBUNASI"}]