[{"id":1502020017,"name":"AIR LAGO"},{"id":1502020018,"name":"BADAK TEKURUNG"},{"id":1502020004,"name":"DURIAN RAMBUN"},{"id":1502020012,"name":"LUBUK BERINGIN"},{"id":1502020008,"name":"LUBUK BIRAH"},{"id":1502020015,"name":"MUARA SIAU"},{"id":1502020014,"name":"PASAR MUARA SIAU"},{"id":1502020009,"name":"PERADUN TEMERAS"},{"id":1502020020,"name":"PULAU RAMAN"},{"id":1502020022,"name":"RANTAU BAYUR"},{"id":1502020016,"name":"RANTAU BIDARO"},{"id":1502020013,"name":"RANTAU MACANG"},{"id":1502020019,"name":"RANTAU PANJANG"},{"id":1502020021,"name":"SEPANTAI RENAH"},{"id":1502020023,"name":"SUNGAI ULAS"},{"id":1502020010,"name":"TELUK SIKUMBANG"},{"id":1502020011,"name":"TIARO"}]