[{"id":7203010015,"name":"BURANGA"},{"id":7203010018,"name":"DONGKALANG"},{"id":7203010003,"name":"KOFALAGADI"},{"id":7203010010,"name":"MASADIAN"},{"id":7203010013,"name":"MATANO"},{"id":7203010014,"name":"MATARAPE"},{"id":7203010023,"name":"MBOKITTA"},{"id":7203010007,"name":"MOROMPAITONGA"},{"id":7203010006,"name":"NGAPAEA"},{"id":7203010008,"name":"PADALAA"},{"id":7203010009,"name":"PADEI DARAT"},{"id":7203010001,"name":"PADEI LAUT"},{"id":7203010021,"name":"PULAU TENGAH"},{"id":7203010012,"name":"PULAU TIGA"},{"id":7203010011,"name":"SAMARENGGA"},{"id":7203010020,"name":"TAFAGAPI"},{"id":7203010019,"name":"TANJUNG HARAPAN"},{"id":7203010022,"name":"TANJUNG TIRAM"},{"id":7203010024,"name":"TANONA"},{"id":7203010005,"name":"TEREBINO"},{"id":7203010004,"name":"TORUKUNO"},{"id":7203010002,"name":"ULUNAMBO"},{"id":7203010016,"name":"ULUNIPA"},{"id":7203010017,"name":"WAWONGKOLONO"}]