[{"id":3602130014,"name":"BUNGUR MEKAR"},{"id":3602130008,"name":"CALUNGBUNGUR"},{"id":3602130015,"name":"CIUYAH"},{"id":3602130001,"name":"MARAYA"},{"id":3602130002,"name":"MARGALUYU"},{"id":3602130011,"name":"MEKARSARI"},{"id":3602130010,"name":"PAJA"},{"id":3602130012,"name":"PAJAGAN"},{"id":3602130013,"name":"PARUNGSARI"},{"id":3602130006,"name":"SAJIRA"},{"id":3602130005,"name":"SAJIRAMEKAR"},{"id":3602130004,"name":"SINDANGSARI"},{"id":3602130009,"name":"SUKAJAYA"},{"id":3602130003,"name":"SUKAMARGA"},{"id":3602130007,"name":"SUKARAME"}]