[{"id":3316020002,"name":"BODEH"},{"id":3316020003,"name":"GEMBYUNGAN"},{"id":3316020013,"name":"KADENGAN"},{"id":3316020010,"name":"KALISARI"},{"id":3316020011,"name":"KEDIREN"},{"id":3316020009,"name":"KUTUKAN"},{"id":3316020018,"name":"NGLIRON"},{"id":3316020006,"name":"PILANG"},{"id":3316020015,"name":"PLOSOREJO"},{"id":3316020005,"name":"RANDUBLATUNG"},{"id":3316020004,"name":"SAMBONGWANGAN"},{"id":3316020008,"name":"SUMBERJO"},{"id":3316020017,"name":"TANGGEL"},{"id":3316020001,"name":"TLOGOTUWUNG"}]