[{"id":3520060024,"name":"BARON"},{"id":3520060016,"name":"BULUKERTO"},{"id":3520060013,"name":"CANDIREJO"},{"id":3520060020,"name":"KEBONAGUNG"},{"id":3520060021,"name":"KEPOLOREJO"},{"id":3520060015,"name":"MAGETAN"},{"id":3520060017,"name":"MANGKUJAYAN"},{"id":3520060025,"name":"PURWOSARI"},{"id":3520060009,"name":"RINGINAGUNG"},{"id":3520060014,"name":"SELOSARI"},{"id":3520060023,"name":"SUKOWINANGUN"},{"id":3520060018,"name":"TAMBAKREJO"},{"id":3520060019,"name":"TAMBRAN"},{"id":3520060022,"name":"TAWANGANOM"}]