[{"id":9418051017,"name":"BERENGGO"},{"id":9418051010,"name":"DELELAH"},{"id":9418051011,"name":"GILO"},{"id":9418051024,"name":"KABOMANGEN"},{"id":9418051015,"name":"KANGGINERI"},{"id":9418051008,"name":"KILUNGGA"},{"id":9418051006,"name":"KIMOBUR"},{"id":9418051026,"name":"KIPINO"},{"id":9418051003,"name":"KOKONDAO"},{"id":9418051025,"name":"KONDANGWI"},{"id":9418051023,"name":"KONIPAGA"},{"id":9418051020,"name":"KUBALO"},{"id":9418051005,"name":"KURIPA"},{"id":9418051022,"name":"MOLOLOWA"},{"id":9418051009,"name":"NOMBORI"},{"id":9418051002,"name":"NUNGGAWI"},{"id":9418051007,"name":"TIMOBUR"},{"id":9418051021,"name":"TINOWENE"},{"id":9418051018,"name":"TUNIBUR"},{"id":9418051012,"name":"UNDI"},{"id":9418051004,"name":"WONDAME"},{"id":9418051016,"name":"WONOLUK"},{"id":9418051019,"name":"WOYI"}]