[{"id":1610040050,"name":"BELANTI"},{"id":1610040048,"name":"KERINJING"},{"id":1610040028,"name":"SERIDALAM"},{"id":1610040036,"name":"SIRING ALAM"},{"id":1610040053,"name":"SKONJING"},{"id":1610040045,"name":"SUKA PINDAH"},{"id":1610040035,"name":"TALANG BALAI BARU I"},{"id":1610040052,"name":"TALANG BALAI BARU II"},{"id":1610040038,"name":"TALANG BALAI LAMA"},{"id":1610040037,"name":"TANJUNG AGAS"},{"id":1610040054,"name":"TANJUNG HARAPAN"},{"id":1610040030,"name":"TANJUNG RAJA"},{"id":1610040031,"name":"TANJUNG RAJA BARAT"},{"id":1610040051,"name":"TANJUNG RAJA SELATAN"},{"id":1610040049,"name":"TANJUNG RAJA TIMUR"},{"id":1610040032,"name":"TANJUNG RAJA UTARA"},{"id":1610040024,"name":"TANJUNG TEMIANG"},{"id":1610040047,"name":"ULAK KERBAU BARU"},{"id":1610040046,"name":"ULAK KERBAU LAMA"}]